TI3D/TI3d.py
TI3D/__init__.py
TI3D-1.0.0.dist-info/LICENSE
TI3D-1.0.0.dist-info/METADATA
TI3D-1.0.0.dist-info/WHEEL
TI3D-1.0.0.dist-info/top_level.txt
TI3D-1.0.0.dist-info/RECORD
