Metadata-Version: 2.1
Name: TI3D
Version: 1.0.0
Summary: A simple 3D rendering libary for python
Author: legolars2800
License-File: LICENSE
